{
  "domain": "nicole-tollefson-ux.squarespace.com",
  "urls": [
    "http://nicole-tollefson-ux.squarespace.com/"
  ],
  "names": [
    "Nicole Tollefson",
    "Hello"
  ],
  "descriptions": [],
  "pictures": [
    "http://nicole-tollefson-ux.squarespace.com/favicon.ico"
  ],
  "hcard": {},
  "rel_mes": [],
  "crawl_start": "2017-05-07T06:35:11",
  "crawl_end": "2017-05-07T06:35:12",
  "num_pages": 4,
  "total_html_size": 169130,
  "servers": [],
  "tags": [],
  "endpoints": {},
  "links_out": 30,
  "links_in": 0,
  "links": {
    "www.wnyc.org": {
      "out": {
        "other": 3
      },
      "score": 1
    },
    "www.youtube.com": {
      "out": {
        "other": 2
      },
      "score": 0.777
    },
    "www.theatlantic.com": {
      "out": {
        "other": 2
      },
      "score": 0.777
    },
    "tech.firstpost.com": {
      "out": {
        "other": 1
      },
      "score": 0.387
    },
    "www.stuffmomnevertoldyou.com": {
      "out": {
        "other": 1
      },
      "score": 0.387
    },
    "techcrunch.com": {
      "out": {
        "other": 1
      },
      "score": 0.387
    },
    "thememorypalace.us": {
      "out": {
        "other": 1
      },
      "score": 0.387
    },
    "peepsforum.com": {
      "out": {
        "other": 1
      },
      "score": 0.387
    },
    "99percentinvisible.org": {
      "out": {
        "other": 1
      },
      "score": 0.387
    },
    "www.nytimes.com": {
      "out": {
        "other": 1
      },
      "score": 0.387
    },
    "www.eathomemade.com": {
      "out": {
        "other": 1
      },
      "score": 0.387
    },
    "www.gocopia.com": {
      "out": {
        "other": 1
      },
      "score": 0.387
    },
    "songexploder.net": {
      "out": {
        "other": 1
      },
      "score": 0.387
    },
    "cuchine.com": {
      "out": {
        "other": 1
      },
      "score": 0.387
    },
    "handup.org": {
      "out": {
        "other": 1
      },
      "score": 0.387
    },
    "feltron.com": {
      "out": {
        "other": 1
      },
      "score": 0.387
    },
    "joyable.com": {
      "out": {
        "other": 1
      },
      "score": 0.387
    },
    "www.calmtech.com": {
      "out": {
        "other": 1
      },
      "score": 0.387
    },
    "josephine.com": {
      "out": {
        "other": 1
      },
      "score": 0.387
    },
    "www.radiolab.org": {
      "out": {
        "other": 1
      },
      "score": 0.387
    },
    "justgetflux.com": {
      "out": {
        "other": 1
      },
      "score": 0.387
    },
    "itunes.apple.com": {
      "out": {
        "other": 1
      },
      "score": 0.387
    },
    "www.rollingstone.com": {
      "out": {
        "other": 1
      },
      "score": 0.387
    },
    "poly-graph.co": {
      "out": {
        "other": 1
      },
      "score": 0.387
    },
    "www.foodrunners.org": {
      "out": {
        "other": 1
      },
      "score": 0.387
    },
    "www.dinnerpartydownload.org": {
      "out": {
        "other": 1
      },
      "score": 0.387
    }
  }
}