{
  "domain": "punkworks.wordpress.com",
  "urls": [
    "https://punkworks.wordpress.com/"
  ],
  "names": [
    "punkworks | the kind of parties where we can drink together and share music and share ideas",
    "punkworks"
  ],
  "descriptions": [
    "the kind of parties where we can drink together and share music and share ideas"
  ],
  "pictures": [
    "https://secure.gravatar.com/blavatar/9cd4d91069bde2b7d705a61b875f7517?s=32",
    "https://secure.gravatar.com/blavatar/9cd4d91069bde2b7d705a61b875f7517?s=200&ts=1495262633"
  ],
  "hcard": {},
  "rel_mes": [],
  "crawl_start": "2017-05-14T04:34:54",
  "crawl_end": "2017-05-14T04:36:42",
  "num_pages": 224,
  "total_html_size": 15433900,
  "servers": [
    "nginx",
    "WordPress.com"
  ],
  "mf2_classes": [
    "h-card",
    "h-feed",
    "h-entry"
  ],
  "tags": [],
  "endpoints": {},
  "links_out": 2774,
  "links_in": 2,
  "links": {
    "wordpress.com": {
      "out": {
        "other": 672
      },
      "score": 1
    },
    "javascript": {
      "out": {
        "other": 610
      },
      "score": 0.988
    },
    "punkworks.files.wordpress.com": {
      "out": {
        "other": 432
      },
      "score": 0.939
    },
    "facebook.com/punkworksindusseldorf": {
      "out": {
        "other": 172
      },
      "score": 0.811
    },
    "twitter.com/punkworks": {
      "out": {
        "other": 172
      },
      "score": 0.811
    },
    "www.instagram.com": {
      "out": {
        "other": 172
      },
      "score": 0.811
    },
    "facebook.com/events": {
      "out": {
        "other": 154
      },
      "score": 0.796
    },
    "gravatar.com": {
      "out": {
        "other": 122
      },
      "score": 0.764
    },
    "www.approximation-festival.de": {
      "out": {
        "other": 94
      },
      "score": 0.728
    },
    "soundcloud.com": {
      "out": {
        "other": 26
      },
      "score": 0.549
    },
    "facebook.com/lifeattrivago": {
      "out": {
        "other": 18
      },
      "score": 0.497
    },
    "www.zakk.de": {
      "out": {
        "other": 16
      },
      "score": 0.482
    },
    "super-flu.de": {
      "out": {
        "other": 14
      },
      "score": 0.462
    },
    "www.cubanitos-bar.de": {
      "out": {
        "other": 14
      },
      "score": 0.462
    },
    "www.thecloche.de": {
      "out": {
        "other": 14
      },
      "score": 0.462
    },
    "www.marinabaranova.net": {
      "out": {
        "other": 12
      },
      "score": 0.442
    },
    "www.baldower.com": {
      "out": {
        "other": 12
      },
      "score": 0.442
    },
    "www.danielwohlmusic.com": {
      "out": {
        "other": 12
      },
      "score": 0.442
    },
    "www.dorianwood.com": {
      "out": {
        "other": 12
      },
      "score": 0.442
    },
    "www.meetup.com": {
      "out": {
        "other": 8
      },
      "score": 0.385
    },
    "facebook.com/CubanitosBar": {
      "out": {
        "other": 8
      },
      "score": 0.385
    },
    "facebook.com/prinzalbertduesseldorf": {
      "out": {
        "other": 4
      },
      "score": 0.289
    },
    "facebook.com/Plöpp-242795345765220": {
      "out": {
        "other": 2
      },
      "score": 0.193
    },
    "facebook.com/goldkantebochum": {
      "out": {
        "other": 2
      },
      "score": 0.193
    },
    "indieweb.org": {
      "in": {
        "other": 2
      },
      "score": 0.0962
    }
  }
}